{
  "project_info": {
    "project_number": "943437980654",
    "firebase_url": "https://e-mart-database-default-rtdb.firebaseio.com",
    "project_id": "e-mart-database",
    "storage_bucket": "e-mart-database.appspot.com"
  },
  "client": [
    {
      "client_info": {
        "mobilesdk_app_id": "1:943437980654:android:c624145d4e66e7fd5264ff",
        "android_client_info": {
          "package_name": "com.example.app2"
        }
      },
      "oauth_client": [
        {
          "client_id": "943437980654-aa0mktefvrj0pc7ocmip2l31epnl2lns.apps.googleusercontent.com",
          "client_type": 3
        }
      ],
      "api_key": [
        {
          "current_key": "AIzaSyCCU-FteD5jNuR-3rj_TUPNyj7ZtPEV8i0"
        }
      ],
      "services": {
        "appinvite_service": {
          "other_platform_oauth_client": [
            {
              "client_id": "943437980654-aa0mktefvrj0pc7ocmip2l31epnl2lns.apps.googleusercontent.com",
              "client_type": 3
            }
          ]
        }
      }
    },
    {
      "client_info": {
        "mobilesdk_app_id": "1:943437980654:android:3b469eb357b6c6705264ff",
        "android_client_info": {
          "package_name": "com.example.app3"
        }
      },
      "oauth_client": [
        {
          "client_id": "943437980654-aa0mktefvrj0pc7ocmip2l31epnl2lns.apps.googleusercontent.com",
          "client_type": 3
        }
      ],
      "api_key": [
        {
          "current_key": "AIzaSyCCU-FteD5jNuR-3rj_TUPNyj7ZtPEV8i0"
        }
      ],
      "services": {
        "appinvite_service": {
          "other_platform_oauth_client": [
            {
              "client_id": "943437980654-aa0mktefvrj0pc7ocmip2l31epnl2lns.apps.googleusercontent.com",
              "client_type": 3
            }
          ]
        }
      }
    },
    {
      "client_info": {
        "mobilesdk_app_id": "1:943437980654:android:c37d1541f86a25e75264ff",
        "android_client_info": {
          "package_name": "com.example.app4"
        }
      },
      "oauth_client": [
        {
          "client_id": "943437980654-aa0mktefvrj0pc7ocmip2l31epnl2lns.apps.googleusercontent.com",
          "client_type": 3
        }
      ],
      "api_key": [
        {
          "current_key": "AIzaSyCCU-FteD5jNuR-3rj_TUPNyj7ZtPEV8i0"
        }
      ],
      "services": {
        "appinvite_service": {
          "other_platform_oauth_client": [
            {
              "client_id": "943437980654-aa0mktefvrj0pc7ocmip2l31epnl2lns.apps.googleusercontent.com",
              "client_type": 3
            }
          ]
        }
      }
    },
    {
      "client_info": {
        "mobilesdk_app_id": "1:943437980654:android:4b9d948c47b64d8d5264ff",
        "android_client_info": {
          "package_name": "com.example.app5"
        }
      },
      "oauth_client": [
        {
          "client_id": "943437980654-aa0mktefvrj0pc7ocmip2l31epnl2lns.apps.googleusercontent.com",
          "client_type": 3
        }
      ],
      "api_key": [
        {
          "current_key": "AIzaSyCCU-FteD5jNuR-3rj_TUPNyj7ZtPEV8i0"
        }
      ],
      "services": {
        "appinvite_service": {
          "other_platform_oauth_client": [
            {
              "client_id": "943437980654-aa0mktefvrj0pc7ocmip2l31epnl2lns.apps.googleusercontent.com",
              "client_type": 3
            }
          ]
        }
      }
    }
  ],
  "configuration_version": "1"
}